README.md
setup.cfg
setup.py
order/__init__.py
order/entities.py
order/errors.py
order/packets.py
order/types.py
order.py.egg-info/PKG-INFO
order.py.egg-info/SOURCES.txt
order.py.egg-info/dependency_links.txt
order.py.egg-info/top_level.txt