Metadata-Version: 2.1
Name: order.py
Version: 0.0.3
Summary: Official Order Python API wrapper
Home-page: https://github.com/ordermsg/order.py
Author: portasynthinca3
Author-email: portasynthinca3@gmail.com
License: MIT
Download-URL: https://github.com/ordermsg/order.py/archive/0.0.1.tar.gz
Keywords: api,api-client
Platform: UNKNOWN
Classifier: Development Status :: 3 - Alpha
Classifier: Intended Audience :: Developers
Classifier: Topic :: Software Development :: Build Tools
Classifier: License :: OSI Approved :: MIT License
Classifier: Programming Language :: Python :: 3
Classifier: Programming Language :: Python :: 3.5
Classifier: Programming Language :: Python :: 3.6
Classifier: Programming Language :: Python :: 3.7
Classifier: Programming Language :: Python :: 3.8
Classifier: Programming Language :: Python :: 3.9
